weather/__init__.py
weather/__main__.py
weather/weather.py
weather_nws_mcp-0.1.9.dist-info/licenses/LICENSE
weather_nws_mcp-0.1.9.dist-info/METADATA
weather_nws_mcp-0.1.9.dist-info/WHEEL
weather_nws_mcp-0.1.9.dist-info/entry_points.txt
weather_nws_mcp-0.1.9.dist-info/top_level.txt
weather_nws_mcp-0.1.9.dist-info/RECORD
