Metadata-Version: 2.4
Name: weather-nws-mcp
Version: 0.1.9
Summary: A Python package for accessing weather data from the National Weather Service (NWS) API
Author-email: 501849930 <501849930@qq.com>
Keywords: weather,nws,api,forecast,alerts
Requires-Python: >=3.11
License-File: LICENSE
Requires-Dist: httpx>=0.28.1
Requires-Dist: mcp[cli]>=1.16.0
Dynamic: license-file
